ingeset_data.py
score.py
train.py
housing_traning_5519-0.1.dist-info/METADATA
housing_traning_5519-0.1.dist-info/WHEEL
housing_traning_5519-0.1.dist-info/entry_points.txt
housing_traning_5519-0.1.dist-info/top_level.txt
housing_traning_5519-0.1.dist-info/RECORD
