Metadata-Version: 2.1
Name: housing_traning_5519
Version: 0.1
Summary: Sample code for coding practice
Author-email: Durga vamsi <durga.koliparthi@tigeranalytics.com>
Project-URL: Homepage, https://github.com/KDurgavamsi/mle-training
Keywords: housing,data training
Classifier: Programming Language :: Python :: 3
Requires-Python: >=3.11
Requires-Dist: numpy
Requires-Dist: pandas
Requires-Dist: scikit-learn
